tno/quantum/optimization/qubo/solvers/__init__.py
tno/quantum/optimization/qubo/solvers/py.typed
tno/quantum/optimization/qubo/solvers/_classical/_iterative_result.py
tno/quantum/optimization/qubo/solvers/_classical/_neighborhood_solver.py
tno/quantum/optimization/qubo/solvers/_classical/_rs_solver.py
tno/quantum/optimization/qubo/solvers/_dqo/__init__.py
tno/quantum/optimization/qubo/solvers/_dqo/_daqo_result.py
tno/quantum/optimization/qubo/solvers/_dqo/_daqo_solver.py
tno/quantum/optimization/qubo/solvers/_dqo/_qaoa_result.py
tno/quantum/optimization/qubo/solvers/_dqo/_qaoa_solver.py
tno/quantum/optimization/qubo/solvers/_dqo/_qnode_factory.py
tno/quantum/optimization/qubo/solvers/_dqo/layers_lib.py
tno/quantum/optimization/qubo/solvers/_dwave/_custom_solver.py
tno/quantum/optimization/qubo/solvers/_dwave/_dimod_sample_set_result.py
tno/quantum/optimization/qubo/solvers/_dwave/_dwave_clique_embedded_simulated_annealing_solver.py
tno/quantum/optimization/qubo/solvers/_dwave/_dwave_clique_sampler_solver.py
tno/quantum/optimization/qubo/solvers/_dwave/_dwave_embedded_simulated_annealing_solver.py
tno/quantum/optimization/qubo/solvers/_dwave/_dwave_parallel_embedding_solver.py
tno/quantum/optimization/qubo/solvers/_dwave/_dwave_sampler_solver.py
tno/quantum/optimization/qubo/solvers/_dwave/_dwave_tiling_solver.py
tno/quantum/optimization/qubo/solvers/_dwave/_exact_sampler_solver.py
tno/quantum/optimization/qubo/solvers/_dwave/_kerberos_sampler_solver.py
tno/quantum/optimization/qubo/solvers/_dwave/_leap_hybrid_solver.py
tno/quantum/optimization/qubo/solvers/_dwave/_random_sampler_solver.py
tno/quantum/optimization/qubo/solvers/_dwave/_simulated_annealing_solver.py
tno/quantum/optimization/qubo/solvers/_dwave/_steepest_descent_solver.py
tno/quantum/optimization/qubo/solvers/_dwave/_tabu_solver.py
tno/quantum/optimization/qubo/solvers/_dwave/_tree_decomposition_solver.py
tno/quantum/optimization/qubo/solvers/_dwave/_utils.py
tno_quantum_optimization_qubo_solvers-1.5.0.dist-info/licenses/LICENSE
tno_quantum_optimization_qubo_solvers-1.5.0.dist-info/METADATA
tno_quantum_optimization_qubo_solvers-1.5.0.dist-info/WHEEL
tno_quantum_optimization_qubo_solvers-1.5.0.dist-info/top_level.txt
tno_quantum_optimization_qubo_solvers-1.5.0.dist-info/RECORD
